srtgo/__init__.py
srtgo/ktx.py
srtgo/srt.py
srtgo/srtgo.py
srtgo-2.2.2.dist-info/licenses/LICENSE
srtgo-2.2.2.dist-info/METADATA
srtgo-2.2.2.dist-info/WHEEL
srtgo-2.2.2.dist-info/entry_points.txt
srtgo-2.2.2.dist-info/top_level.txt
srtgo-2.2.2.dist-info/RECORD
