Metadata-Version: 2.4
Name: srtgo
Version: 2.2.2
Summary: SRTgo: K-Train Reservation Helper
Author-email: DKim <lapis42@gmail.com>
License: MIT License
Project-URL: Homepage, https://github.com/lapis42/srtgo
Classifier: Programming Language :: Python :: 3
Requires-Python: >=3.10
License-File: LICENSE
Requires-Dist: click
Requires-Dist: curl_cffi
Requires-Dist: requests
Requires-Dist: inquirer>=3.4
Requires-Dist: keyring
Requires-Dist: PyCryptodome
Requires-Dist: prompt_toolkit>=3
Requires-Dist: python-telegram-bot
Requires-Dist: termcolor
Dynamic: license-file
